dockable/__init__.py
dockable/__main__.py
dockable/_version.py
dockable/cliargs.py
dockable/types.py
dockable/builtin/__init__.py
dockable/builtin/module.yml
dockable/builtin/ansible/__init__.py
dockable/builtin/ansible/handlers.yml.jinja
dockable/builtin/ansible/module.yml
dockable/builtin/ansible/steps.py
dockable/builtin/apt/__init__.py
dockable/builtin/apt/handlers.yml.jinja
dockable/builtin/apt/module.yml
dockable/builtin/pip/__init__.py
dockable/builtin/pip/handlers.yml.jinja
dockable/builtin/pip/module.yml
dockable/builtin/pip/steps.py
dockable/engine/__init__.py
dockable/engine/graph.py
dockable/engine/render.py
dockable/engine/unfold.py
dockable/load/__init__.py
dockable/load/file_loader.py
dockable/load/file_steps.py
dockable/load/module.py
dockable/meta/__init__.py
dockable/meta/handlers.yml.jinja
dockable/meta/module.yml
dockable/raw/__init__.py
dockable/raw/handlers.yml.jinja
dockable/raw/module.yml
dockable/raw/steps.py
dockable/releases/__init__.py
dockable/releases/binary.yml.jinja
dockable/releases/module.yml
dockable/releases/source.yml.jinja
dockable-0.5.dist-info/LICENSE
dockable-0.5.dist-info/METADATA
dockable-0.5.dist-info/WHEEL
dockable-0.5.dist-info/top_level.txt
dockable-0.5.dist-info/RECORD
