Metadata-Version: 2.1
Name: dockable
Version: 0.5
Summary: ansible for dockerfiles
Home-page: https://gitlab.com/dockable/dockable.git
Author: Martin Zihlmann
Author-email: martizih@outlook.com
License: MIT
Classifier: Programming Language :: Python :: 3
Classifier: License :: Other/Proprietary License
Classifier: Operating System :: OS Independent
Requires-Python: >=3.10
License-File: LICENSE
Requires-Dist: pyaml
Requires-Dist: jinja2
Requires-Dist: arketip (>=0.4)
Requires-Dist: pip-api
Requires-Dist: networkx
